dangr_rt/__init__.py
dangr_rt/arguments_analyzer.py
dangr_rt/dangr_analysis.py
dangr_rt/dangr_argparse.py
dangr_rt/dangr_simulation.py
dangr_rt/dangr_types.py
dangr_rt/dependency_analyzer.py
dangr_rt/expression.py
dangr_rt/jasm_findings.py
dangr_rt/jasm_mock/sw_brk_jasm_out.json
dangr_rt/simulator.py
dangr_rt/texput.log
dangr_rt/variable_factory.py
dangr_rt/variables.py
dangr_rt-1.0.1.dist-info/METADATA
dangr_rt-1.0.1.dist-info/WHEEL
dangr_rt-1.0.1.dist-info/RECORD
